{
  "author": "Brad Chesney",
  "checksums": {
    "Rakefile": "f37e6131fe7de9a49b09d31596f5fbf1",
    "manifests/init.pp": "7c8641d2d9911fcd7fbb39084d999519",
    "Modulefile": "cce776c3b0efef2e43ffeb48373cfdf5",
    "spec/spec.opts": "a600ded995d948e393fbe2320ba8e51c",
    "tests/init.pp": "57724e0baa0f179c072e150db52f40c3",
    "spec/spec_helper.rb": "3ea886dd135e120afa31e0aab12e85b0",
    "README.markdown": "8e1ffacfadc14beb7f83751f3719d3fc"
  },
  "dependencies": [
    {
      "name": "puppetlabs/apt",
      "version_requirement": "1.5.2"
    }
  ],
  "description": "Intel provides drivers for their video chipsets, the experience is better with the new and improved capabilities, so make it easier to take advantage of their kindness.",
  "license": "Creative Commons",
  "name": "BradChesney79-intel_graphics_install",
  "project_page": "",
  "source": "https://github.com/bradchesney79/intel_graphics_install",
  "summary": "Install the Intel provided linux graphics kernel drivers",
  "types": [],
  "version": "0.1.0"
}